setup.py
ranked_vote/__init__.py
ranked_vote/ballot.py
ranked_vote.egg-info/PKG-INFO
ranked_vote.egg-info/SOURCES.txt
ranked_vote.egg-info/dependency_links.txt
ranked_vote.egg-info/top_level.txt
ranked_vote/format/__init__.py