Metadata-Version: 1.0
Name: ranked-vote
Version: 0.0.1
Summary: Tools for working with ranked-vote data
Home-page: https://github.com/ranked-vote/ranked-vote-tools
Author: Paul Butler
Author-email: rcv@paulbutler.org
License: UNKNOWN
Platform: UNKNOWN
